<?xml version="1.0" encoding="UTF-8"?>
<entity-mappings xmlns="http://xmlns.jcp.org/xml/ns/persistence/orm"
                 xmlns:xsi="http://www.w3.org/2001/XMLSchema-instance"
                 xsi:schemaLocation="http://xmlns.jcp.org/xml/ns/persistence/orm http://xmlns.jcp.org/xml/ns/persistence/orm_2_2.xsd"
                 version="2.2">
    <named-native-query name="Project.findByProjectName" result-set-mapping="projectSearchResponse">
        <query>
            <![CDATA[
                select project_id as projectId
                     , project_name as projectName
                     , to_char(project_start_date, 'YYYY-MM-DD') as projectStartDate
                     , to_char(project_end_date, 'YYYY-MM-DD') as projectEndDate
                     , to_char(create_dt, 'YYYY-MM-DD HH24:MI:SS') as createDate
                     , to_char(update_dt, 'YYYY-MM-DD HH24:MI:SS') as updateDate
                  from project
                 where project_name like concat('%', :projectName, '%')
            ]]>
        </query>
    </named-native-query>

    <sql-result-set-mapping name="projectSearchResponse">
        <constructor-result target-class="com.aljjabaegi.api.domain.project.record.ProjectSearchResponse">
            <column name="projectId"/>
            <column name="projectName"/>
            <column name="projectStartDate"/>
            <column name="projectEndDate"/>
            <column name="createDate"/>
            <column name="updateDate"/>
        </constructor-result>
    </sql-result-set-mapping>
</entity-mappings>